cloe_sql_transformations/__init__.py
cloe_sql_transformations/main.py
cloe_sql_transformations/py.typed
cloe_sql_transformations/model/__init__.py
cloe_sql_transformations/model/artifacts.py
cloe_sql_transformations/model/conversion_template_generator.py
cloe_sql_transformations/model/custom_dataflow_generator.py
cloe_sql_transformations/model/sql_syntax.py
cloe_sql_transformations/model/dataflow/__init__.py
cloe_sql_transformations/model/dataflow/column_mapping_generator.py
cloe_sql_transformations/model/dataflow/dataflow_generator.py
cloe_sql_transformations/model/dataflow/lookup_generator.py
cloe_sql_transformations/model/dataflow/source_table_generator.py
cloe_sql_transformations/sql/__init__.py
cloe_sql_transformations/sql/sql_templates.py
cloe_sql_transformations/sql/templates/__init__.py
cloe_sql_transformations/sql/templates/snowflake_sql/__init__.py
cloe_sql_transformations/sql/templates/snowflake_sql/conversion/__init__.py
cloe_sql_transformations/sql/templates/snowflake_sql/conversion/array.sql.jinja
cloe_sql_transformations/sql/templates/snowflake_sql/conversion/binary.sql.jinja
cloe_sql_transformations/sql/templates/snowflake_sql/conversion/boolean.sql.jinja
cloe_sql_transformations/sql/templates/snowflake_sql/conversion/date.sql.jinja
cloe_sql_transformations/sql/templates/snowflake_sql/conversion/float.sql.jinja
cloe_sql_transformations/sql/templates/snowflake_sql/conversion/number.sql.jinja
cloe_sql_transformations/sql/templates/snowflake_sql/conversion/object.sql.jinja
cloe_sql_transformations/sql/templates/snowflake_sql/conversion/time.sql.jinja
cloe_sql_transformations/sql/templates/snowflake_sql/conversion/timestamp_ltz.sql.jinja
cloe_sql_transformations/sql/templates/snowflake_sql/conversion/timestamp_ntz.sql.jinja
cloe_sql_transformations/sql/templates/snowflake_sql/conversion/timestamp_tz.sql.jinja
cloe_sql_transformations/sql/templates/snowflake_sql/conversion/varchar.sql.jinja
cloe_sql_transformations-1.0.11.dist-info/METADATA
cloe_sql_transformations-1.0.11.dist-info/WHEEL
cloe_sql_transformations-1.0.11.dist-info/RECORD
