Metadata-Version: 2.4
Name: cloe-sql-transformations
Version: 1.0.11
Summary: Generates ready to use SQL DMLs based on metadata
Author-email: initions <ICSMC_EXT_PYPIORG@accenture.com>
License: MIT
Classifier: Development Status :: 5 - Production/Stable
Classifier: Environment :: Console
Classifier: Intended Audience :: Developers
Classifier: License :: OSI Approved :: MIT License
Classifier: Operating System :: OS Independent
Classifier: Programming Language :: Python :: 3
Classifier: Topic :: Database
Requires-Python: <3.12,>=3.11
Requires-Dist: cloe-metadata~=2.2.2
Requires-Dist: jinja2~=3.1.2
Requires-Dist: typer[all]~=0.16.0
